{
  "main": {
    "name":"Finance Entry",
    "occupation":"(Your Occupation Here)",
    "description":"Here will be your description. Use this to describe what you do or whatever you feel best describes yourself to a potential employer",
    "image":"profilepic.jpg",
    "bio":"Use this bio section as your way of describing yourself and saying what you do, what technologies you like to use or feel most comfortable with, describing your personality, or whatever else you feel like throwing in.",
    "contactmessage":"Here is where you should write your message to readers to have them get in contact with you.",
    "email": "finance_entry@yahoo.com",
    "phone": "+852 9030 0891",
    "address":{
      "street":"(Your Street)",
      "city":"Hong Kong"
    },
    "website": "http://www.financeentry.com.hk",
    "resumedownload":"http://timbakerdev.com",
    "social":[
      {
        "name":"facebook",
        "url":"http://facebook.com/FinanceEntry",
        "className":"fa fa-facebook"
      },
      {
        "name":"twitter",
        "url":"http://twitter.com",
        "className":"fa fa-twitter"
      },
      {
        "name":"google-plus",
        "url":"http://googleplus.com/",
        "className":"fa fa-google-plus"
      },
      {
        "name":"linkedin",
        "url":"https://www.linkedin.com/",
        "className":"fa fa-linkedin"
      },
      {
        "name":"instagram",
        "url":"http://instagram.com/",
        "className":"fa fa-instagram"
      },
      {
        "name":"github",
        "url":"http://github.com/",
        "className":"fa fa-github"
      },
      {
        "name":"skype",
        "url":"http://skype.com",
        "className":"fa fa-skype"
      }
    ]
  },
  "resume":{
    "skillmessage":"Here you can create a short write-up of your skills to show off to employers",
    "education":[
      {
        "school":"University?",
        "degree":"Masters in Beer tasting",
        "graduated":"April 2007",
        "description":"Describe your experience at school, what you learned, what useful skills you have acquired etc."
      },
      {
        "school":"School #1 Maybe College?",
        "degree":"What did you study 101",
        "graduated":"March 2003",
        "description":"Describe your experience at school, what you learned, what useful skills you have acquired etc."
      }
    ],
    "work":[
      {
        "company":"Awesome Design Studio",
        "title":"Senior UX God ",
        "years":"March 2010 - Present",
        "description":"Describe work, special projects, notable achievements, what technologies you have been working with, and anything else that would be useful for an employer to know."
      },
      {
        "company":"Super Cool Studio",
        "title":"Junior bug fixer",
        "years":"March 2007 - February 2010",
        "description":"Describe work, special projects, notable achievements, what technologies you have been working with, and anything else that would be useful for an employer to know."
      }
    ],
    "skills":[
      {
        "name":"Git",
        "level":"60%"
      },
      {
        "name":"Illustrator",
        "level":"55%"
      },
      {
        "name":"ReactJs",
        "level":"50%"
      },
      {
        "name":"CSS",
        "level":"90%"
      },
      {
        "name":"HTML5",
        "level":"80%"
      },
      {
        "name":"VueJs",
        "level":"50%"
      },
      {
        "name":"MongoDB",
        "level":"80%"
      }
    ]
  },
  "courses":{
    "classes":[
      {
        "title": "Junior Financial Analyst",
        "duration": "2 Weeks",
        "time": "Mon-Fri 10:00am - 1:00pm",
        "language": "Cantonese supplemented w/ English",
        "fee": "$4500HKD",
        "background": "This course is designed to teach students, who have passion in financial industry, the basic knowledge of finance and different job functionalities. \n學員將會被安排面對面與不同金融專業人任接觸和交談。課程將介紹現時金融界的基本概念，能讓學員認識到市場、銀行、證券公司和交易所；資本轉移，各類證券以及投資決策過程的知識。此外，課程內容亦會介紹投資決策於股票上所用的工具，以及基本會計概念和Execl的使用方法，從而令學員學習到基礎分析、技術分析和流程分析的技巧。課程概念將透過案例研究和使用本地市場例子作解說。",
        "topics": "This 2 -week course will cover: \nIntroduction of financial market; Investment Bank vs Commercial Bank \nThe need for Capital market; Introduction of types of securities \nHow to Analyze a Company? \nBasic Accounting \nIntroduction to Excel Modeling \nIntroduction of different job types in financial market and MEET the Professionals \nHK Exchange & Clearing Visit",
        "location": "TBD",
        "instructor": "Ray So",
        "about": "Mr. So 為量智學院有限公司的其中一位創辦人。學院致力於為青少年提供財務和技術技能，為新時代的挑戰和機遇做好準備。學院主要著重於非傳統的教育，不能從常規高中教育中吸取的知識。Mr. So 亦於 HKU SPACE 任教多年，主要教授金融課程，有多年教育經驗. \n Mr. So was working in the financial industry for over 18 years at various reputable Investment Banks such as Goldman Sachs, Merrill Lynch, Nomura, ING Bank and Deutsche Bank."
      }
    ]
  },
  "portfolio":{
    "projects": [
      {
        "title":"Canadian Wanderlust",
        "category":"My Travel Blog for my post-university travels",
        "image":"canadian-wanderlust.jpg",
        "url":"https://www.canadianwanderlust.com"
      },
      {
        "title":"Fury Fighting Gear",
        "category":"(offline now) A fighting gear company I started",
        "image":"fury-fighting-gear.jpg",
        "url":"http://www.timbakerdev.com"
      },
      {
        "title":"Original Thai Food",
        "category":"Website I built for a restaurant I like in Thailand",
        "image":"original-thai-food.jpg",
        "url":"http://www.timbakerdev.com/originalthaifood.github.io"
      },
      {
        "title":"Resume Website",
        "category":"A React based resume website template",
        "image":"resume-website.jpg",
        "url":"http://www.timbakerdev.com"
      },
      {
        "title":"Smirkspace",
        "category":"(MVP Only) A React and Meteor based chat University project.",
        "image":"smirkspace.jpg",
        "url":"http://www.smirkspace.com"
      }
    ]
  },
  "testimonials":{
    "testimonials":[
      {
        "text":"Here you should write some nice things that someone has said about you. No lies though, employers can tell when you are lying.",
        "user":"Kareem Abdul Jabbar"
      },
      {
        "text":"That Tim Baker must be one of the most brilliant developers I've ever met! It is amazing that nobody has hired him yet. Hey you, you should hire this guy, he may be fresh out of University and have zero on the job experience but I am confident that he will be one of your best developers in no time!",
        "user":"Steve Wozniak... impersonator"
      }
    ]
  }
}
